promptflow/rag/__init__.py
promptflow/rag/_build_mlindex.py
promptflow/rag/_get_langchain_retriever.py
promptflow/rag/_utils/__init__.py
promptflow/rag/_utils/_open_ai_utils.py
promptflow/rag/config/__init__.py
promptflow/rag/config/_azure_ai_search_config.py
promptflow/rag/config/_connection_config.py
promptflow/rag/config/_embeddings_model_config.py
promptflow/rag/config/_index_config.py
promptflow/rag/config/_index_data_source.py
promptflow/rag/constants/__init__.py
promptflow/rag/constants/_common.py
promptflow_rag-0.1.0.dist-info/METADATA
promptflow_rag-0.1.0.dist-info/WHEEL
promptflow_rag-0.1.0.dist-info/top_level.txt
promptflow_rag-0.1.0.dist-info/RECORD
