Metadata-Version: 2.1
Name: promptflow-rag
Version: 0.1.0
Summary: Prompt flow index build
Home-page: https://github.com/microsoft/promptflow
Author: Microsoft Corporation
Author-email: aml-pt-eng@microsoft.com
Project-URL: Bug Reports, https://github.com/microsoft/promptflow/issues
Project-URL: Source, https://github.com/microsoft/promptflow
Classifier: Development Status :: 4 - Beta
Classifier: Programming Language :: Python
Classifier: Programming Language :: Python :: 3
Classifier: Programming Language :: Python :: 3 :: Only
Classifier: Programming Language :: Python :: 3.8
Classifier: Programming Language :: Python :: 3.9
Classifier: Programming Language :: Python :: 3.10
Classifier: Programming Language :: Python :: 3.11
Classifier: Programming Language :: Python :: 3.12
Classifier: License :: OSI Approved :: MIT License
Classifier: Operating System :: OS Independent
Requires-Python: <4.0,>=3.8
Requires-Dist: azureml-rag[azure,cognitive_search,document_parsing,langchain]
Requires-Dist: openai
